anid/__init__.py
anid/anid.py
anid/downloader.py
anid-0.2.2.dist-info/LICENSE
anid-0.2.2.dist-info/METADATA
anid-0.2.2.dist-info/WHEEL
anid-0.2.2.dist-info/entry_points.txt
anid-0.2.2.dist-info/top_level.txt
anid-0.2.2.dist-info/RECORD
